sbhs_robomaster/__init__.py
sbhs_robomaster/auto_connect.py
sbhs_robomaster/client.py
sbhs_robomaster/data.py
sbhs_robomaster/feed.py
sbhs_robomaster/push_receiver.py
sbhs_robomaster-1.0.0.dist-info/METADATA
sbhs_robomaster-1.0.0.dist-info/WHEEL
sbhs_robomaster-1.0.0.dist-info/licenses/LICENSE
sbhs_robomaster-1.0.0.dist-info/RECORD
